primer_designer/__init__.py
primer_designer/__main__.py
primer_designer/designer.py
primer_designer/utils.py
primer_designer-0.2.0.dist-info/DESCRIPTION.rst
primer_designer-0.2.0.dist-info/METADATA
primer_designer-0.2.0.dist-info/RECORD
primer_designer-0.2.0.dist-info/WHEEL
primer_designer-0.2.0.dist-info/entry_points.txt
primer_designer-0.2.0.dist-info/metadata.json
primer_designer-0.2.0.dist-info/top_level.txt
